pyreportlib/__init__.py
pyreportlib/entail.pdf
pyreportlib/entail.png
pyreportlib/get_documents.py
pyreportlib/make_documents.py
pyreportlib/tailor.png
pyreportlib/template.docx
pyreportlib/utils/__init__.py
pyreportlib/utils/excel_utils.py
pyreportlib-0.1.2.dist-info/WHEEL
pyreportlib-0.1.2.dist-info/METADATA
pyreportlib-0.1.2.dist-info/RECORD
