Metadata-Version: 2.1
Name: pyreportlib
Version: 0.1.2
Summary: 
Author: bernt sørby
Author-email: bsorby@gmail.com
Requires-Python: >=3.8,<4.0
Classifier: Programming Language :: Python :: 3
Classifier: Programming Language :: Python :: 3.10
Classifier: Programming Language :: Python :: 3.8
Classifier: Programming Language :: Python :: 3.9
Requires-Dist: matplotlib (>=3.3.2,<4.0.0)
Requires-Dist: pandas (>=1.1.2,<2.0.0)
Requires-Dist: pylatex (>=1.4.0,<2.0.0)
Requires-Dist: python-docx (>=0.8.10,<0.9.0)
Requires-Dist: xlrd (>=1.2.0,<2.0.0)
